distributed_logging/__init__.py
distributed_logging/parse_yaml.py
distributed_logging/portalocker/__init__.py
distributed_logging/portalocker/constants.py
distributed_logging/portalocker/exceptions.py
distributed_logging/portalocker/portalocker.py
distributed_logging/portalocker/queue.py
distributed_logging/portalocker/utils.py
distributed_logging-0.0.3.dist-info/METADATA
distributed_logging-0.0.3.dist-info/WHEEL
distributed_logging-0.0.3.dist-info/top_level.txt
distributed_logging-0.0.3.dist-info/RECORD
