Metadata-Version: 2.1
Name: distributed-logging
Version: 0.0.3
Summary: This is my distributed logging package
Home-page: https://github.com/ckf10000/distributed-logging
Author: ckf10000
Author-email: ckf10000@sina.com
Classifier: Programming Language :: Python :: 3
Classifier: License :: OSI Approved :: MIT License
Classifier: Operating System :: OS Independent
Requires-Dist: PyYAML >=6.0.1
Requires-Dist: pywin32 >=303 ; sys_platform != "linux"
